DPSDV/__init__.py
DPSDV/demo.py
DPSDV/errors.py
DPSDV/evaluation.py
DPSDV/sdv.py
DPSDV/utils.py
DPSDV/constraints/__init__.py
DPSDV/constraints/base.py
DPSDV/constraints/errors.py
DPSDV/constraints/tabular.py
DPSDV/constraints/utils.py
DPSDV/lite/__init__.py
DPSDV/lite/tabular.py
DPSDV/metadata/__init__.py
DPSDV/metadata/dataset.py
DPSDV/metadata/errors.py
DPSDV/metadata/table.py
DPSDV/metadata/utils.py
DPSDV/metadata/visualization.py
DPSDV/metrics/__init__.py
DPSDV/metrics/demos.py
DPSDV/metrics/relational.py
DPSDV/metrics/tabular.py
DPSDV/metrics/timeseries.py
DPSDV/relational/__init__.py
DPSDV/relational/base.py
DPSDV/relational/hma.py
DPSDV/sampling/__init__.py
DPSDV/sampling/tabular.py
DPSDV/tabular/__init__.py
DPSDV/tabular/base.py
DPSDV/tabular/base_mwem.py
DPSDV/tabular/copulagan.py
DPSDV/tabular/copulas.py
DPSDV/tabular/ctgan.py
DPSDV/tabular/mwem.py
DPSDV/tabular/utils.py
DPSDV/timeseries/__init__.py
DPSDV/timeseries/base.py
DPSDV/timeseries/deepecho.py
DPSDV-0.0.3.dist-info/METADATA
DPSDV-0.0.3.dist-info/WHEEL
DPSDV-0.0.3.dist-info/top_level.txt
DPSDV-0.0.3.dist-info/RECORD
