Metadata-Version: 2.1
Name: DPSDV
Version: 0.0.3
Summary: Creating a Differential Privacy securing Synthetic Data Generation for tabular, relational and time series data.
Home-page: https://github.com/AmanPriyanshu/DPSDV
Author: Aman Priyanshu
Author-email: amanpriyanshusms2001@gmail.com
License: MIT license
Keywords: differential-privacy sdv synthetic-data synhtetic-data-generation timeseries single-table multi-table
Classifier: Development Status :: 2 - Pre-Alpha
Classifier: Intended Audience :: Developers
Classifier: License :: OSI Approved :: MIT License
Classifier: Natural Language :: English
Classifier: Programming Language :: Python :: 3
Classifier: Programming Language :: Python :: 3.6
Classifier: Programming Language :: Python :: 3.7
Classifier: Programming Language :: Python :: 3.8
Classifier: Programming Language :: Python :: 3.9
Requires-Python: >=3.6,<3.10
Requires-Dist: Faker (<10,>=3.0.0)
Requires-Dist: graphviz (<1,>=0.13.2)
Requires-Dist: pandas (<2,>=1.1.3)
Requires-Dist: tqdm (<5,>=4.15)
Requires-Dist: copulas (<0.8,>=0.7.0)
Requires-Dist: ctgan (<0.6,>=0.5.1)
Requires-Dist: deepecho (<0.4,>=0.3.0.post1)
Requires-Dist: rdt (<0.7,>=0.6.2)
Requires-Dist: sdmetrics (<0.6,>=0.5.0)
Requires-Dist: numpy (<1.20.0,>=1.18.0) ; python_version < "3.7"
Requires-Dist: numpy (<2,>=1.20.0) ; python_version >= "3.7"
Provides-Extra: dev
Requires-Dist: bumpversion (<0.6,>=0.5.3) ; extra == 'dev'
Requires-Dist: pip (>=9.0.1) ; extra == 'dev'
Requires-Dist: watchdog (<0.9,>=0.8.3) ; extra == 'dev'
Requires-Dist: docutils (<0.18,>=0.12) ; extra == 'dev'
Requires-Dist: m2r2 (<0.3,>=0.2.5) ; extra == 'dev'
Requires-Dist: nbsphinx (<0.7,>=0.5.0) ; extra == 'dev'
Requires-Dist: Sphinx (<3.3,>=3) ; extra == 'dev'
Requires-Dist: pydata-sphinx-theme (<0.5) ; extra == 'dev'
Requires-Dist: markupsafe (<2.1.0) ; extra == 'dev'
Requires-Dist: Jinja2 (<3,>=2) ; extra == 'dev'
Requires-Dist: flake8 (<4,>=3.7.7) ; extra == 'dev'
Requires-Dist: flake8-absolute-import (<2,>=1.0) ; extra == 'dev'
Requires-Dist: flake8-docstrings (<2,>=1.5.0) ; extra == 'dev'
Requires-Dist: flake8-sfs (<0.1,>=0.0.3) ; extra == 'dev'
Requires-Dist: isort (<5,>=4.3.4) ; extra == 'dev'
Requires-Dist: autoflake (<2,>=1.1) ; extra == 'dev'
Requires-Dist: autopep8 (<1.6,>=1.4.3) ; extra == 'dev'
Requires-Dist: twine (<4,>=1.10.0) ; extra == 'dev'
Requires-Dist: wheel (>=0.30.0) ; extra == 'dev'
Requires-Dist: coverage (<6,>=4.5.1) ; extra == 'dev'
Requires-Dist: tox (<4,>=2.9.1) ; extra == 'dev'
Requires-Dist: invoke ; extra == 'dev'
Requires-Dist: pytest (>=3.4.2) ; extra == 'dev'
Requires-Dist: pytest-cov (>=2.6.0) ; extra == 'dev'
Requires-Dist: pytest-rerunfailures (>10) ; extra == 'dev'
Requires-Dist: jupyter (<2,>=1.0.0) ; extra == 'dev'
Requires-Dist: rundoc (<0.5,>=0.4.3) ; extra == 'dev'
Provides-Extra: pomegranate
Requires-Dist: pomegranate (<0.14.2,>=0.13.4) ; (python_version < "3.7") and extra == 'pomegranate'
Requires-Dist: pomegranate (<0.15,>=0.14.1) ; (python_version >= "3.7") and extra == 'pomegranate'
Provides-Extra: test
Requires-Dist: pytest (>=3.4.2) ; extra == 'test'
Requires-Dist: pytest-cov (>=2.6.0) ; extra == 'test'
Requires-Dist: pytest-rerunfailures (>10) ; extra == 'test'
Requires-Dist: jupyter (<2,>=1.0.0) ; extra == 'test'
Requires-Dist: rundoc (<0.5,>=0.4.3) ; extra == 'test'
